{
  "as_of": "2026-07-08",
  "generated_at": "2026-07-08T11:08:27.389Z",
  "module_id": "data_reality_audit_v0_1",
  "status": "audit_available",
  "overall_reality": "mixed_non_real",
  "headline": "当前页面含 6 个非真实或来源未验证层。模型结构可看，市场结论不可直接用。",
  "layers": [
    {
      "id": "akshare_provider_doctor",
      "name": "AKShare环境预检",
      "source_file": "model_outputs/provider_runs/akshare_etf_bridge_doctor.json",
      "as_of": null,
      "generated_at": "2026-07-08T11:07:20.863404+00:00",
      "reality": "provider_doctor_ok",
      "confidence_for_market_use": "medium",
      "counts": {
        "checks": 2,
        "blocked_checks": 0
      },
      "reading": "AKShare provider environment preflight passed.",
      "install_hint": "python3 -m pip install -r providers/requirements.txt",
      "run_hint": "npm run provider:akshare && npm run provider:akshare:validate && npm run provider:akshare:inspect"
    },
    {
      "id": "akshare_provider_run",
      "name": "AKShare真实数据探测",
      "source_file": "model_outputs/provider_runs/akshare_etf_bridge_2026-07-08.json",
      "as_of": "2026-07-08",
      "generated_at": "2026-07-08T11:08:24.685420+00:00",
      "reality": "provider_run_ok",
      "confidence_for_market_use": "medium",
      "counts": {
        "records": 11,
        "warnings": 0,
        "errors": 0
      },
      "errors": [],
      "warnings": [],
      "reading": "AKShare real provider completed with 11 rows. Flow review still needs observed-source coverage checks."
    },
    {
      "id": "flow_price",
      "name": "资金量价",
      "source_file": "sector_flow_review.json",
      "as_of": "2026-07-08",
      "generated_at": "2026-07-08T11:08:25.884Z",
      "reality": "mock",
      "confidence_for_market_use": "low",
      "source_counts": {
        "akshare_provider_flow_observations": 33,
        "mock_observation_collector": 188,
        "string_node": 100
      },
      "counts": {
        "sectors": 31,
        "representative_direct_flow_inputs": 11,
        "representative_price_volume_confirmations": 11
      },
      "reading": "模型组件可运行，但当前资金量价节点来自 mock/fixture 来源，不能当作真实市场信号。"
    },
    {
      "id": "news",
      "name": "新闻层",
      "source_file": "news_review.json",
      "as_of": "2026-07-07",
      "generated_at": "2026-07-07T14:41:34.408Z",
      "reality": "unknown",
      "confidence_for_market_use": "low",
      "counts": {
        "collected_items": 24,
        "matched_events": 8,
        "observations": 10,
        "affected_sectors": 7
      },
      "reading": "新闻层来源不明。"
    },
    {
      "id": "sector_modules",
      "name": "估值/基本面/资金量价三模块",
      "source_file": "sector_module_review.json",
      "as_of": "2026-07-08",
      "generated_at": "2026-07-08T11:08:26.478Z",
      "reality": "manual_seed",
      "confidence_for_market_use": "low",
      "source_counts": {
        "valuation:manual_seed": 31,
        "fundamental:manual_seed": 31,
        "flow_price:from_sector_flow_review": 31
      },
      "counts": {
        "sectors": 31,
        "provider_mapped_representative_sectors": 11,
        "framework_only_sectors": 20,
        "wait_for_confirmation": 24,
        "expensive_momentum": 1,
        "cheap_with_flow": 1,
        "value_trap_risk": 5
      },
      "reading": "估值和基本面是 manual_seed，可解释结构，但不是实时估值或财报数据。"
    },
    {
      "id": "etf_decision_readiness",
      "name": "ETF行动准备度",
      "source_file": "etf_decision_readiness.json",
      "as_of": "2026-07-08",
      "generated_at": "2026-07-08T11:08:26.799Z",
      "reality": "decision_gate_blocked",
      "confidence_for_market_use": "low",
      "counts": {
        "sectors": 31,
        "small_position_candidate": 0,
        "confirmation_candidate": 0,
        "watch_for_persistence": 0,
        "wait_for_real_flow": 0,
        "wait_for_confirmation": 0,
        "blocked_non_real_source": 11,
        "not_covered": 20,
        "avoid_or_reduce_watch": 0
      },
      "blockers": [
        {
          "id": "non_real_flow_source",
          "reading": "行业资金量价仍来自 mock、fixture 或未验证来源。"
        },
        {
          "id": "manual_valuation_fundamental",
          "reading": "估值和基本面模块仍包含手工种子输入。"
        }
      ],
      "reading": "暂不能指导买入 ETF：行业资金量价仍来自 mock、fixture 或未验证来源。"
    },
    {
      "id": "sector_rotation",
      "name": "行业轮动",
      "source_file": "sector_rotation_intelligence.json",
      "as_of": "2026-07-08",
      "generated_at": "2026-07-08T11:08:26.026Z",
      "reality": "derived_from_non_real",
      "confidence_for_market_use": "low",
      "input_layers": [
        {
          "id": "flow_price",
          "reality": "mock"
        },
        {
          "id": "news",
          "reality": "unknown"
        }
      ],
      "reading": "该层是解释层，上游仍含非真实输入，因此只能看结构，不能当真实市场结论。"
    },
    {
      "id": "general_pool_analysis",
      "name": "通用池模型",
      "source_file": "general_pool_analysis.json",
      "as_of": "2026-07-08",
      "generated_at": "2026-07-08T11:08:26.654Z",
      "reality": "contract_output_source_unverified",
      "confidence_for_market_use": "low",
      "counts": {
        "pools": 33,
        "sp500": 1,
        "a_share_industries": 31
      },
      "reading": "通用池模型契约可用，但当前发布 JSON 没有携带可验证 provider source，不能视为实时真实行情判断。"
    },
    {
      "id": "rotation_history",
      "name": "轮动历史",
      "source_file": "sector_rotation_history.json",
      "as_of": "2026-07-08",
      "generated_at": "2026-07-08T11:08:26.335Z",
      "reality": "derived_from_non_real",
      "confidence_for_market_use": "low",
      "input_layers": [
        {
          "id": "sector_rotation",
          "reality": "derived_from_non_real"
        }
      ],
      "reading": "该层是解释层，上游仍含非真实输入，因此只能看结构，不能当真实市场结论。"
    }
  ],
  "warnings": [
    "资金量价: 模型组件可运行，但当前资金量价节点来自 mock/fixture 来源，不能当作真实市场信号。",
    "新闻层: 新闻层来源不明。",
    "估值/基本面/资金量价三模块: 估值和基本面是 manual_seed，可解释结构，但不是实时估值或财报数据。",
    "ETF行动准备度: 暂不能指导买入 ETF：行业资金量价仍来自 mock、fixture 或未验证来源。",
    "行业轮动: 该层是解释层，上游仍含非真实输入，因此只能看结构，不能当真实市场结论。",
    "通用池模型: 通用池模型契约可用，但当前发布 JSON 没有携带可验证 provider source，不能视为实时真实行情判断。",
    "轮动历史: 该层是解释层，上游仍含非真实输入，因此只能看结构，不能当真实市场结论。"
  ],
  "interpretation_boundary": [
    "This audit labels data origin and freshness. It does not change model scores.",
    "mock, fixture, manual_seed, and derived_from_non_real layers are not live market evidence.",
    "A layer can have a valid model contract while still using non-real inputs.",
    "Use this audit before reading any ranking or decision label as market evidence."
  ]
}
