{
  "status": "ok",
  "errors": [],
  "warnings": [],
  "as_of": "2026-07-09",
  "counts": {
    "dates": 3,
    "row_records_total": 33,
    "sector_flow_records_total": 3,
    "latest_row_records": 11,
    "expected_representative_codes": 11,
    "missing_representative_codes": 0,
    "enable_candidates": 11
  },
  "overall_recommendation": "review_candidates_before_enabling",
  "row_findings": [
    {
      "sector_id": "brokerage",
      "node_id": "brokerage_etf_flow",
      "fund_code": "512000",
      "fund_name": "券商ETF华宝",
      "close": 0.542,
      "amount": 1393908958.0,
      "latest_share": 74097037312.0,
      "estimated_flow": 481622622.208,
      "enable_candidate": true,
      "blocking_reason": ""
    },
    {
      "sector_id": "bank_insurance",
      "node_id": "bank_insurance_etf_flow",
      "fund_code": "512800",
      "fund_name": "银行ETF华宝",
      "close": 0.761,
      "amount": 813588827.0,
      "latest_share": 13865079808.0,
      "estimated_flow": -447468000.0,
      "enable_candidate": true,
      "blocking_reason": ""
    },
    {
      "sector_id": "semiconductor",
      "node_id": "semiconductor_etf_flow",
      "fund_code": "512480",
      "fund_name": "半导体ETF国联安",
      "close": 1.471,
      "amount": 2594965472.0,
      "latest_share": 16910007296.0,
      "estimated_flow": -100028000.0,
      "enable_candidate": true,
      "blocking_reason": ""
    },
    {
      "sector_id": "ai_computer",
      "node_id": "ai_computer_etf_flow",
      "fund_code": "159819",
      "fund_name": "人工智能ETF易方达",
      "close": 2.185,
      "amount": 1083559059.655,
      "latest_share": 11173229568.0,
      "estimated_flow": 122360000.0,
      "enable_candidate": true,
      "blocking_reason": ""
    },
    {
      "sector_id": "communication_electronics",
      "node_id": "communication_electronics_etf_flow",
      "fund_code": "515880",
      "fund_name": "通信ETF国泰",
      "close": 0.807,
      "amount": 7102781938.0,
      "latest_share": 68297774080.0,
      "estimated_flow": 1625298103.296,
      "enable_candidate": true,
      "blocking_reason": ""
    },
    {
      "sector_id": "new_energy_ev",
      "node_id": "new_energy_ev_etf_flow",
      "fund_code": "515030",
      "fund_name": "新能源车ETF华夏",
      "close": 1.714,
      "amount": 214913322.0,
      "latest_share": 1639384000.0,
      "estimated_flow": 10284000.0,
      "enable_candidate": true,
      "blocking_reason": ""
    },
    {
      "sector_id": "healthcare_pharma",
      "node_id": "healthcare_pharma_etf_flow",
      "fund_code": "512010",
      "fund_name": "医药ETF易方达",
      "close": 0.356,
      "amount": 560774637.0,
      "latest_share": 49089694976.0,
      "estimated_flow": 243504000.0,
      "enable_candidate": true,
      "blocking_reason": ""
    },
    {
      "sector_id": "consumer",
      "node_id": "consumer_etf_flow",
      "fund_code": "159928",
      "fund_name": "消费ETF汇添富",
      "close": 0.618,
      "amount": 283347154.54,
      "latest_share": 23372628992.0,
      "estimated_flow": 34608000.0,
      "enable_candidate": true,
      "blocking_reason": ""
    },
    {
      "sector_id": "defense_military",
      "node_id": "defense_military_etf_flow",
      "fund_code": "512660",
      "fund_name": "军工ETF国泰",
      "close": 1.243,
      "amount": 353464296.0,
      "latest_share": 5469080064.0,
      "estimated_flow": 64636000.00000001,
      "enable_candidate": true,
      "blocking_reason": ""
    },
    {
      "sector_id": "resources_materials",
      "node_id": "resources_materials_etf_flow",
      "fund_code": "512400",
      "fund_name": "有色金属ETF南方",
      "close": 1.745,
      "amount": 1204320293.0,
      "latest_share": 12654039040.0,
      "estimated_flow": -44497332.480000004,
      "enable_candidate": true,
      "blocking_reason": ""
    },
    {
      "sector_id": "real_estate_infra",
      "node_id": "real_estate_infra_etf_flow",
      "fund_code": "512200",
      "fund_name": "房地产ETF南方",
      "close": 1.189,
      "amount": 79824550.0,
      "latest_share": 2605097904.0,
      "estimated_flow": -4756000.0,
      "enable_candidate": true,
      "blocking_reason": ""
    }
  ],
  "sector_flow_findings": [
    {
      "column": "brokerage_etf_flow",
      "value": 481622622.208,
      "has_value": true
    },
    {
      "column": "bank_insurance_etf_flow",
      "value": -447468000.0,
      "has_value": true
    },
    {
      "column": "semiconductor_etf_flow",
      "value": -100028000.0,
      "has_value": true
    },
    {
      "column": "ai_computer_etf_flow",
      "value": 122360000.0,
      "has_value": true
    },
    {
      "column": "communication_electronics_etf_flow",
      "value": 1625298103.296,
      "has_value": true
    },
    {
      "column": "new_energy_ev_etf_flow",
      "value": 10284000.0,
      "has_value": true
    },
    {
      "column": "healthcare_pharma_etf_flow",
      "value": 243504000.0,
      "has_value": true
    },
    {
      "column": "consumer_etf_flow",
      "value": 34608000.0,
      "has_value": true
    },
    {
      "column": "defense_military_etf_flow",
      "value": 64636000.00000001,
      "has_value": true
    },
    {
      "column": "resources_materials_etf_flow",
      "value": -44497332.480000004,
      "has_value": true
    },
    {
      "column": "real_estate_infra_etf_flow",
      "value": -4756000.0,
      "has_value": true
    }
  ],
  "source_recommendations": [
    {
      "node_id": "brokerage_etf_flow",
      "sector_id": "brokerage",
      "fund_code": "512000",
      "recommendation": "candidate_for_manual_review",
      "reason": "Latest row has positive price, positive amount, and non-empty estimated_flow."
    },
    {
      "node_id": "bank_insurance_etf_flow",
      "sector_id": "bank_insurance",
      "fund_code": "512800",
      "recommendation": "candidate_for_manual_review",
      "reason": "Latest row has positive price, positive amount, and non-empty estimated_flow."
    },
    {
      "node_id": "semiconductor_etf_flow",
      "sector_id": "semiconductor",
      "fund_code": "512480",
      "recommendation": "candidate_for_manual_review",
      "reason": "Latest row has positive price, positive amount, and non-empty estimated_flow."
    },
    {
      "node_id": "ai_computer_etf_flow",
      "sector_id": "ai_computer",
      "fund_code": "159819",
      "recommendation": "candidate_for_manual_review",
      "reason": "Latest row has positive price, positive amount, and non-empty estimated_flow."
    },
    {
      "node_id": "communication_electronics_etf_flow",
      "sector_id": "communication_electronics",
      "fund_code": "515880",
      "recommendation": "candidate_for_manual_review",
      "reason": "Latest row has positive price, positive amount, and non-empty estimated_flow."
    },
    {
      "node_id": "new_energy_ev_etf_flow",
      "sector_id": "new_energy_ev",
      "fund_code": "515030",
      "recommendation": "candidate_for_manual_review",
      "reason": "Latest row has positive price, positive amount, and non-empty estimated_flow."
    },
    {
      "node_id": "healthcare_pharma_etf_flow",
      "sector_id": "healthcare_pharma",
      "fund_code": "512010",
      "recommendation": "candidate_for_manual_review",
      "reason": "Latest row has positive price, positive amount, and non-empty estimated_flow."
    },
    {
      "node_id": "consumer_etf_flow",
      "sector_id": "consumer",
      "fund_code": "159928",
      "recommendation": "candidate_for_manual_review",
      "reason": "Latest row has positive price, positive amount, and non-empty estimated_flow."
    },
    {
      "node_id": "defense_military_etf_flow",
      "sector_id": "defense_military",
      "fund_code": "512660",
      "recommendation": "candidate_for_manual_review",
      "reason": "Latest row has positive price, positive amount, and non-empty estimated_flow."
    },
    {
      "node_id": "resources_materials_etf_flow",
      "sector_id": "resources_materials",
      "fund_code": "512400",
      "recommendation": "candidate_for_manual_review",
      "reason": "Latest row has positive price, positive amount, and non-empty estimated_flow."
    },
    {
      "node_id": "real_estate_infra_etf_flow",
      "sector_id": "real_estate_infra",
      "fund_code": "512200",
      "recommendation": "candidate_for_manual_review",
      "reason": "Latest row has positive price, positive amount, and non-empty estimated_flow."
    }
  ],
  "ranked_by_amount": [
    {
      "sector_id": "communication_electronics",
      "node_id": "communication_electronics_etf_flow",
      "fund_code": "515880",
      "fund_name": "通信ETF国泰",
      "close": 0.807,
      "amount": 7102781938.0,
      "latest_share": 68297774080.0,
      "estimated_flow": 1625298103.296,
      "enable_candidate": true,
      "blocking_reason": ""
    },
    {
      "sector_id": "semiconductor",
      "node_id": "semiconductor_etf_flow",
      "fund_code": "512480",
      "fund_name": "半导体ETF国联安",
      "close": 1.471,
      "amount": 2594965472.0,
      "latest_share": 16910007296.0,
      "estimated_flow": -100028000.0,
      "enable_candidate": true,
      "blocking_reason": ""
    },
    {
      "sector_id": "brokerage",
      "node_id": "brokerage_etf_flow",
      "fund_code": "512000",
      "fund_name": "券商ETF华宝",
      "close": 0.542,
      "amount": 1393908958.0,
      "latest_share": 74097037312.0,
      "estimated_flow": 481622622.208,
      "enable_candidate": true,
      "blocking_reason": ""
    },
    {
      "sector_id": "resources_materials",
      "node_id": "resources_materials_etf_flow",
      "fund_code": "512400",
      "fund_name": "有色金属ETF南方",
      "close": 1.745,
      "amount": 1204320293.0,
      "latest_share": 12654039040.0,
      "estimated_flow": -44497332.480000004,
      "enable_candidate": true,
      "blocking_reason": ""
    },
    {
      "sector_id": "ai_computer",
      "node_id": "ai_computer_etf_flow",
      "fund_code": "159819",
      "fund_name": "人工智能ETF易方达",
      "close": 2.185,
      "amount": 1083559059.655,
      "latest_share": 11173229568.0,
      "estimated_flow": 122360000.0,
      "enable_candidate": true,
      "blocking_reason": ""
    },
    {
      "sector_id": "bank_insurance",
      "node_id": "bank_insurance_etf_flow",
      "fund_code": "512800",
      "fund_name": "银行ETF华宝",
      "close": 0.761,
      "amount": 813588827.0,
      "latest_share": 13865079808.0,
      "estimated_flow": -447468000.0,
      "enable_candidate": true,
      "blocking_reason": ""
    },
    {
      "sector_id": "healthcare_pharma",
      "node_id": "healthcare_pharma_etf_flow",
      "fund_code": "512010",
      "fund_name": "医药ETF易方达",
      "close": 0.356,
      "amount": 560774637.0,
      "latest_share": 49089694976.0,
      "estimated_flow": 243504000.0,
      "enable_candidate": true,
      "blocking_reason": ""
    },
    {
      "sector_id": "defense_military",
      "node_id": "defense_military_etf_flow",
      "fund_code": "512660",
      "fund_name": "军工ETF国泰",
      "close": 1.243,
      "amount": 353464296.0,
      "latest_share": 5469080064.0,
      "estimated_flow": 64636000.00000001,
      "enable_candidate": true,
      "blocking_reason": ""
    },
    {
      "sector_id": "consumer",
      "node_id": "consumer_etf_flow",
      "fund_code": "159928",
      "fund_name": "消费ETF汇添富",
      "close": 0.618,
      "amount": 283347154.54,
      "latest_share": 23372628992.0,
      "estimated_flow": 34608000.0,
      "enable_candidate": true,
      "blocking_reason": ""
    },
    {
      "sector_id": "new_energy_ev",
      "node_id": "new_energy_ev_etf_flow",
      "fund_code": "515030",
      "fund_name": "新能源车ETF华夏",
      "close": 1.714,
      "amount": 214913322.0,
      "latest_share": 1639384000.0,
      "estimated_flow": 10284000.0,
      "enable_candidate": true,
      "blocking_reason": ""
    },
    {
      "sector_id": "real_estate_infra",
      "node_id": "real_estate_infra_etf_flow",
      "fund_code": "512200",
      "fund_name": "房地产ETF南方",
      "close": 1.189,
      "amount": 79824550.0,
      "latest_share": 2605097904.0,
      "estimated_flow": -4756000.0,
      "enable_candidate": true,
      "blocking_reason": ""
    }
  ],
  "ranked_by_estimated_flow": [
    {
      "sector_id": "communication_electronics",
      "node_id": "communication_electronics_etf_flow",
      "fund_code": "515880",
      "fund_name": "通信ETF国泰",
      "close": 0.807,
      "amount": 7102781938.0,
      "latest_share": 68297774080.0,
      "estimated_flow": 1625298103.296,
      "enable_candidate": true,
      "blocking_reason": ""
    },
    {
      "sector_id": "brokerage",
      "node_id": "brokerage_etf_flow",
      "fund_code": "512000",
      "fund_name": "券商ETF华宝",
      "close": 0.542,
      "amount": 1393908958.0,
      "latest_share": 74097037312.0,
      "estimated_flow": 481622622.208,
      "enable_candidate": true,
      "blocking_reason": ""
    },
    {
      "sector_id": "healthcare_pharma",
      "node_id": "healthcare_pharma_etf_flow",
      "fund_code": "512010",
      "fund_name": "医药ETF易方达",
      "close": 0.356,
      "amount": 560774637.0,
      "latest_share": 49089694976.0,
      "estimated_flow": 243504000.0,
      "enable_candidate": true,
      "blocking_reason": ""
    },
    {
      "sector_id": "ai_computer",
      "node_id": "ai_computer_etf_flow",
      "fund_code": "159819",
      "fund_name": "人工智能ETF易方达",
      "close": 2.185,
      "amount": 1083559059.655,
      "latest_share": 11173229568.0,
      "estimated_flow": 122360000.0,
      "enable_candidate": true,
      "blocking_reason": ""
    },
    {
      "sector_id": "defense_military",
      "node_id": "defense_military_etf_flow",
      "fund_code": "512660",
      "fund_name": "军工ETF国泰",
      "close": 1.243,
      "amount": 353464296.0,
      "latest_share": 5469080064.0,
      "estimated_flow": 64636000.00000001,
      "enable_candidate": true,
      "blocking_reason": ""
    },
    {
      "sector_id": "consumer",
      "node_id": "consumer_etf_flow",
      "fund_code": "159928",
      "fund_name": "消费ETF汇添富",
      "close": 0.618,
      "amount": 283347154.54,
      "latest_share": 23372628992.0,
      "estimated_flow": 34608000.0,
      "enable_candidate": true,
      "blocking_reason": ""
    },
    {
      "sector_id": "new_energy_ev",
      "node_id": "new_energy_ev_etf_flow",
      "fund_code": "515030",
      "fund_name": "新能源车ETF华夏",
      "close": 1.714,
      "amount": 214913322.0,
      "latest_share": 1639384000.0,
      "estimated_flow": 10284000.0,
      "enable_candidate": true,
      "blocking_reason": ""
    },
    {
      "sector_id": "real_estate_infra",
      "node_id": "real_estate_infra_etf_flow",
      "fund_code": "512200",
      "fund_name": "房地产ETF南方",
      "close": 1.189,
      "amount": 79824550.0,
      "latest_share": 2605097904.0,
      "estimated_flow": -4756000.0,
      "enable_candidate": true,
      "blocking_reason": ""
    },
    {
      "sector_id": "resources_materials",
      "node_id": "resources_materials_etf_flow",
      "fund_code": "512400",
      "fund_name": "有色金属ETF南方",
      "close": 1.745,
      "amount": 1204320293.0,
      "latest_share": 12654039040.0,
      "estimated_flow": -44497332.480000004,
      "enable_candidate": true,
      "blocking_reason": ""
    },
    {
      "sector_id": "semiconductor",
      "node_id": "semiconductor_etf_flow",
      "fund_code": "512480",
      "fund_name": "半导体ETF国联安",
      "close": 1.471,
      "amount": 2594965472.0,
      "latest_share": 16910007296.0,
      "estimated_flow": -100028000.0,
      "enable_candidate": true,
      "blocking_reason": ""
    },
    {
      "sector_id": "bank_insurance",
      "node_id": "bank_insurance_etf_flow",
      "fund_code": "512800",
      "fund_name": "银行ETF华宝",
      "close": 0.761,
      "amount": 813588827.0,
      "latest_share": 13865079808.0,
      "estimated_flow": -447468000.0,
      "enable_candidate": true,
      "blocking_reason": ""
    }
  ],
  "inspector_id": "akshare_etf_bridge_export_inspector",
  "generated_at": "2026-07-09T11:38:08.726661+00:00",
  "row_csv": "data/provider_exports/a_share_etf_daily.csv",
  "sector_flow_csv": "data/provider_exports/a_share_sector_flow.csv"
}
