{
  "id": "environmental_protection_policy_news",
  "kind": "node",
  "name": "Environmental Protection Policy News",
  "data_type": "news",
  "category": "sector_policy",
  "frequency": "event",
  "coverage_status": "framework_only",
  "classification": "sw_level1_framework_slot",
  "description": "Structured policy or regulatory news affecting expectations for the sector. Sector context: Environmental protection pool for waste treatment, water treatment, and environmental services.",
  "source": {
    "provider": "official_media_or_ai_classifier",
    "status": "planned"
  }
}
